[{"line":1,"elements":[{"line":3,"name":"Login with valid credential","description":"","type":"background","keyword":"Background","steps":[{"result":{"duration":1405811300,"status":"passed"},"line":4,"name":"user on login page","match":{"location":"belajar.stepdef.LoginStepDef.userIsOnLoginPage()"},"keyword":"Given "},{"result":{"duration":967697200,"status":"passed"},"line":5,"name":"user input username with \"standard_user\"","match":{"arguments":[{"val":"\"standard_user\"","offset":25}],"location":"belajar.stepdef.LoginStepDef.userInputUsernameWith(java.lang.String)"},"keyword":"And "},{"result":{"duration":1560889100,"status":"passed"},"line":6,"name":"user input password with \"secret_sauce\"","match":{"arguments":[{"val":"\"secret_sauce\"","offset":25}],"location":"belajar.stepdef.LoginStepDef.userInputPasswordWith(java.lang.String)"},"keyword":"And "},{"result":{"duration":655713000,"status":"passed"},"line":7,"name":"user click login button","match":{"location":"belajar.stepdef.LoginStepDef.userClickOnLoginButton()"},"keyword":"When "},{"result":{"duration":1625745500,"status":"passed"},"line":8,"name":"user on home page","match":{"location":"belajar.stepdef.LoginStepDef.userisOnHomePage()"},"keyword":"Then "}]},{"start_timestamp":"2022-12-29T15:07:50.221Z","before":[{"result":{"duration":13497101400,"status":"passed"},"match":{"location":"belajar.cucumberhook.beforeAll()"}}],"line":10,"name":"user checkout 2 items","description":"","id":"checkout;user-checkout-2-items","after":[{"result":{"duration":660128500,"status":"passed"},"match":{"location":"belajar.cucumberhook.afterAll()"}}],"type":"scenario","keyword":"Scenario","steps":[{"result":{"duration":260306500,"status":"passed"},"line":11,"name":"user add first product","match":{"location":"belajar.stepdef.Checkout.userAddFirstProduct()"},"keyword":"When "},{"result":{"duration":1714427800,"status":"passed"},"line":12,"name":"user add second product","match":{"location":"belajar.stepdef.Checkout.userAddSecondProduct()"},"keyword":"And "},{"result":{"duration":703811000,"status":"passed"},"line":13,"name":"validate total item","match":{"location":"belajar.stepdef.Checkout.validateTotalItem()"},"keyword":"And "},{"result":{"duration":295378000,"status":"passed"},"line":14,"name":"user click cart","match":{"location":"belajar.stepdef.Checkout.userClickCart()"},"keyword":"And "},{"result":{"duration":7100292200,"status":"passed"},"line":15,"name":"user click checkout","match":{"location":"belajar.stepdef.Checkout.userClickCheckout()"},"keyword":"And "},{"result":{"duration":1851561500,"status":"passed"},"line":16,"name":"user on Information page","match":{"location":"belajar.stepdef.Checkout.userOnInformationPage()"},"keyword":"Then "},{"result":{"duration":224037500,"status":"passed"},"line":17,"name":"user input first name \"nizam\"","match":{"arguments":[{"val":"\"nizam\"","offset":22}],"location":"belajar.stepdef.Checkout.inputFirstName(java.lang.String)"},"keyword":"When "},{"result":{"duration":658303600,"status":"passed"},"line":18,"name":"user input last name \"aditya\"","match":{"arguments":[{"val":"\"aditya\"","offset":21}],"location":"belajar.stepdef.Checkout.inputLastName(java.lang.String)"},"keyword":"And "},{"result":{"duration":1591921600,"status":"passed"},"line":19,"name":"user input postal code \"12345\"","match":{"arguments":[{"val":"\"12345\"","offset":23}],"location":"belajar.stepdef.Checkout.inputZipCode(java.lang.String)"},"keyword":"And "},{"result":{"duration":609014600,"status":"passed"},"line":20,"name":"user click continue","match":{"location":"belajar.stepdef.Checkout.clickContinue()"},"keyword":"And "},{"result":{"duration":1266744000,"status":"passed"},"line":21,"name":"user on overview page","match":{"location":"belajar.stepdef.Checkout.validateoveerviewPage()"},"keyword":"Then "},{"result":{"duration":3645862900,"status":"passed"},"line":22,"name":"user click finish","match":{"location":"belajar.stepdef.Checkout.clickFinish()"},"keyword":"When "},{"result":{"duration":2783155500,"status":"passed"},"line":23,"name":"user on thanks page","match":{"location":"belajar.stepdef.Checkout.validateLastPage()"},"keyword":"Then "}]}],"name":"Checkout","description":"","id":"checkout","keyword":"Feature","uri":"file:src/test/resources/features/checkout.feature","tags":[]},{"line":1,"elements":[{"start_timestamp":"2022-12-29T15:08:33.344Z","before":[{"result":{"duration":12577754500,"status":"passed"},"match":{"location":"belajar.cucumberhook.beforeAll()"}}],"line":11,"name":"login valid username and password","description":"","id":"login;login-valid-username-and-password;;2","after":[{"result":{"duration":721509000,"status":"passed"},"match":{"location":"belajar.cucumberhook.afterAll()"}}],"type":"scenario","keyword":"Scenario Outline","steps":[{"result":{"duration":1908255700,"status":"passed"},"line":4,"name":"user on login page","match":{"location":"belajar.stepdef.LoginStepDef.userIsOnLoginPage()"},"keyword":"Given "},{"result":{"duration":166282300,"status":"passed"},"line":5,"name":"user input username with \"standard_user\"","match":{"arguments":[{"val":"\"standard_user\"","offset":25}],"location":"belajar.stepdef.LoginStepDef.userInputUsernameWith(java.lang.String)"},"keyword":"And "},{"result":{"duration":1816240500,"status":"passed"},"line":6,"name":"user input password with \"secret_sauce\"","match":{"arguments":[{"val":"\"secret_sauce\"","offset":25}],"location":"belajar.stepdef.LoginStepDef.userInputPasswordWith(java.lang.String)"},"keyword":"And "},{"result":{"duration":1082921500,"status":"passed"},"line":7,"name":"user click login button","match":{"location":"belajar.stepdef.LoginStepDef.userClickOnLoginButton()"},"keyword":"When "},{"result":{"duration":1657469500,"status":"passed"},"line":8,"name":"user on home page","match":{"location":"belajar.stepdef.LoginStepDef.userisOnHomePage()"},"keyword":"Then "}]},{"start_timestamp":"2022-12-29T15:08:53.298Z","before":[{"result":{"duration":14048103300,"status":"passed"},"match":{"location":"belajar.cucumberhook.beforeAll()"}}],"line":12,"name":"login valid username and password","description":"","id":"login;login-valid-username-and-password;;3","after":[{"result":{"duration":904796900,"status":"passed"},"match":{"location":"belajar.cucumberhook.afterAll()"}}],"type":"scenario","keyword":"Scenario Outline","steps":[{"result":{"duration":1627334500,"status":"passed"},"line":4,"name":"user on login page","match":{"location":"belajar.stepdef.LoginStepDef.userIsOnLoginPage()"},"keyword":"Given "},{"result":{"duration":195812400,"status":"passed"},"line":5,"name":"user input username with \"problem_user\"","match":{"arguments":[{"val":"\"problem_user\"","offset":25}],"location":"belajar.stepdef.LoginStepDef.userInputUsernameWith(java.lang.String)"},"keyword":"And "},{"result":{"duration":1155718000,"status":"passed"},"line":6,"name":"user input password with \"secret_sauce\"","match":{"arguments":[{"val":"\"secret_sauce\"","offset":25}],"location":"belajar.stepdef.LoginStepDef.userInputPasswordWith(java.lang.String)"},"keyword":"And "},{"result":{"duration":647065800,"status":"passed"},"line":7,"name":"user click login button","match":{"location":"belajar.stepdef.LoginStepDef.userClickOnLoginButton()"},"keyword":"When "},{"result":{"duration":2314839900,"status":"passed"},"line":8,"name":"user on home page","match":{"location":"belajar.stepdef.LoginStepDef.userisOnHomePage()"},"keyword":"Then "}]},{"start_timestamp":"2022-12-29T15:09:14.217Z","before":[{"result":{"duration":17139514800,"status":"passed"},"match":{"location":"belajar.cucumberhook.beforeAll()"}}],"line":14,"name":"login with invalid username and password","description":"","id":"login;login-with-invalid-username-and-password","after":[{"result":{"duration":679591200,"status":"passed"},"match":{"location":"belajar.cucumberhook.afterAll()"}}],"type":"scenario","keyword":"Scenario","steps":[{"result":{"duration":1021020700,"status":"passed"},"line":15,"name":"user on login page","match":{"location":"belajar.stepdef.LoginStepDef.userIsOnLoginPage()"},"keyword":"Given "},{"result":{"duration":1048625700,"status":"passed"},"line":16,"name":"user input username with \"standard\"","match":{"arguments":[{"val":"\"standard\"","offset":25}],"location":"belajar.stepdef.LoginStepDef.userInputUsernameWith(java.lang.String)"},"keyword":"And "},{"result":{"duration":1726762100,"status":"passed"},"line":17,"name":"user input password with \"secret_sauce\"","match":{"arguments":[{"val":"\"secret_sauce\"","offset":25}],"location":"belajar.stepdef.LoginStepDef.userInputPasswordWith(java.lang.String)"},"keyword":"And "},{"result":{"duration":1127591700,"status":"passed"},"line":18,"name":"user click login button","match":{"location":"belajar.stepdef.LoginStepDef.userClickOnLoginButton()"},"keyword":"When "},{"result":{"duration":1060358300,"status":"passed"},"line":19,"name":"user get error message","match":{"location":"belajar.stepdef.LoginStepDef.userGetErrorMessage()"},"keyword":"Then "}]}],"name":"Login","description":"","id":"login","keyword":"Feature","uri":"file:src/test/resources/features/login.feature","tags":[]},{"line":1,"elements":[{"line":3,"name":"Login with valid credential","description":"","type":"background","keyword":"Background","steps":[{"result":{"duration":1494703700,"status":"passed"},"line":4,"name":"user on login page","match":{"location":"belajar.stepdef.LoginStepDef.userIsOnLoginPage()"},"keyword":"Given "},{"result":{"duration":992466200,"status":"passed"},"line":5,"name":"user input username with \"standard_user\"","match":{"arguments":[{"val":"\"standard_user\"","offset":25}],"location":"belajar.stepdef.LoginStepDef.userInputUsernameWith(java.lang.String)"},"keyword":"And "},{"result":{"duration":1109984600,"status":"passed"},"line":6,"name":"user input password with \"secret_sauce\"","match":{"arguments":[{"val":"\"secret_sauce\"","offset":25}],"location":"belajar.stepdef.LoginStepDef.userInputPasswordWith(java.lang.String)"},"keyword":"And "},{"result":{"duration":641231300,"status":"passed"},"line":7,"name":"user click login button","match":{"location":"belajar.stepdef.LoginStepDef.userClickOnLoginButton()"},"keyword":"When "},{"result":{"duration":1656653600,"status":"passed"},"line":8,"name":"user on home page","match":{"location":"belajar.stepdef.LoginStepDef.userisOnHomePage()"},"keyword":"Then "}]},{"start_timestamp":"2022-12-29T15:09:38.046Z","before":[{"result":{"duration":11499228400,"status":"passed"},"match":{"location":"belajar.cucumberhook.beforeAll()"}}],"line":10,"name":"User sort product","description":"","id":"sorting;user-sort-product","after":[{"result":{"duration":687118300,"status":"passed"},"match":{"location":"belajar.cucumberhook.afterAll()"}}],"type":"scenario","keyword":"Scenario","steps":[{"result":{"duration":681539100,"status":"passed"},"line":11,"name":"user click sorting button","match":{"location":"belajar.stepdef.Sorting.userClickSortingButton()"},"keyword":"When "},{"result":{"duration":1663469900,"status":"passed"},"line":12,"name":"user press button","match":{"location":"belajar.stepdef.Sorting.userPressButton()"},"keyword":"And "},{"result":{"duration":1035020700,"status":"passed"},"line":13,"name":"product sorted from low to high","match":{"location":"belajar.stepdef.Sorting.sortedLowToHigh()"},"keyword":"Then "}]}],"name":"Sorting","description":"","id":"sorting","keyword":"Feature","uri":"file:src/test/resources/features/sorting.feature","tags":[]}]